MANIFEST.in
README
ez_setup.py
setup.py
lolcut/__init__.py
lolcut/cue.py
lolcut/main.py
lolcut.egg-info/PKG-INFO
lolcut.egg-info/SOURCES.txt
lolcut.egg-info/dependency_links.txt
lolcut.egg-info/entry_points.txt
lolcut.egg-info/requires.txt
lolcut.egg-info/top_level.txt