Metadata-Version: 1.0
Name: lolcut
Version: 0.1.0
Summary: Splits loseless images into tracks, renames tracks, sets tags
Home-page: https://bitbucket.org/boh/lolcut
Author: Dmitry Soldatov
Author-email: grapescan@gmail.com
License: GPL
Download-URL: https://bitbucket.org/boh/lolcut/downloads/lolcut-0.1.0.tar.gz
Keywords: shntool loseless image cue sheet split flac ape wv tag
Platform: all
Classifier: Development Status :: 5 - Production/Stable
Classifier: Environment :: Console
Classifier: Intended Audience :: End Users/Desktop
Classifier: License :: OSI Approved :: GNU General Public License (GPL)
Classifier: Natural Language :: English
Classifier: Operating System :: POSIX :: Linux
Classifier: Programming Language :: Python
Classifier: Topic :: Multimedia :: Sound/Audio :: Conversion
